adventurex_shit/__init__.py
adventurex_shit/bounty_hunter.py
adventurex_shit/chaos_simulator.py
adventurex_shit/incident_reporter.py
adventurex_shit/toilet_detective.py
adventurex_shit-1.0.0.dist-info/licenses/LICENSE
adventurex_shit-1.0.0.dist-info/METADATA
adventurex_shit-1.0.0.dist-info/WHEEL
adventurex_shit-1.0.0.dist-info/top_level.txt
adventurex_shit-1.0.0.dist-info/RECORD
