Metadata-Version: 2.4
Name: adventurex-shit
Version: 1.0.0
Summary: A humorous Python module commemorating the legendary AdventureX 2025 bathroom incident
Home-page: https://github.com/adventurex/shit-incident
Author: Anonymous Hackathon Participant
Author-email: mystery@adventurex.com
Project-URL: Bug Reports, https://github.com/adventurex/shit-incident/issues
Project-URL: Source, https://github.com/adventurex/shit-incident
Project-URL: Bounty Hunter, https://adventurex.com/bounty/5000
Keywords: adventurex hackathon bathroom humor toilet incident
Classifier: Development Status :: 5 - Production/Stable
Classifier: Intended Audience :: Developers
Classifier: License :: OSI Approved :: MIT License
Classifier: Operating System :: OS Independent
Classifier: Programming Language :: Python :: 3
Classifier: Programming Language :: Python :: 3.7
Classifier: Programming Language :: Python :: 3.8
Classifier: Programming Language :: Python :: 3.9
Classifier: Programming Language :: Python :: 3.10
Classifier: Programming Language :: Python :: 3.11
Classifier: Topic :: Software Development :: Libraries :: Python Modules
Classifier: Topic :: Games/Entertainment
Requires-Python: >=3.7
License-File: LICENSE
Dynamic: author
Dynamic: author-email
Dynamic: classifier
Dynamic: description
Dynamic: description-content-type
Dynamic: home-page
Dynamic: keywords
Dynamic: license-file
Dynamic: project-url
Dynamic: requires-python
Dynamic: summary
